{
	"cmake" : 
	{
		"generator" : 
		{
			"multiConfig" : false,
			"name" : "Ninja"
		},
		"paths" : 
		{
			"cmake" : "C:/Program Files/CMake/bin/cmake.exe",
			"cpack" : "C:/Program Files/CMake/bin/cpack.exe",
			"ctest" : "C:/Program Files/CMake/bin/ctest.exe",
			"root" : "C:/Program Files/CMake/share/cmake-3.30"
		},
		"version" : 
		{
			"isDirty" : false,
			"major" : 3,
			"minor" : 30,
			"patch" : 4,
			"string" : "3.30.4",
			"suffix" : ""
		}
	},
	"objects" : 
	[
		{
			"jsonFile" : "codemodel-v2-99a09a5b39a0a17b3680.json",
			"kind" : "codemodel",
			"version" : 
			{
				"major" : 2,
				"minor" : 7
			}
		},
		{
			"jsonFile" : "cache-v2-5daace7ef2e46f219fae.json",
			"kind" : "cache",
			"version" : 
			{
				"major" : 2,
				"minor" : 0
			}
		},
		{
			"jsonFile" : "cmakeFiles-v1-69e4fbce497111f0cc07.json",
			"kind" : "cmakeFiles",
			"version" : 
			{
				"major" : 1,
				"minor" : 1
			}
		}
	],
	"reply" : 
	{
		"client-agp" : 
		{
			"cache-v2" : 
			{
				"jsonFile" : "cache-v2-5daace7ef2e46f219fae.json",
				"kind" : "cache",
				"version" : 
				{
					"major" : 2,
					"minor" : 0
				}
			},
			"cmakeFiles-v1" : 
			{
				"jsonFile" : "cmakeFiles-v1-69e4fbce497111f0cc07.json",
				"kind" : "cmakeFiles",
				"version" : 
				{
					"major" : 1,
					"minor" : 1
				}
			},
			"codemodel-v2" : 
			{
				"jsonFile" : "codemodel-v2-99a09a5b39a0a17b3680.json",
				"kind" : "codemodel",
				"version" : 
				{
					"major" : 2,
					"minor" : 7
				}
			}
		}
	}
}
